{
  "scientific_name": "Macrolepiota procera",
  "author_citation": "(Scop.) Singer 1948",
  "accepted_name": "Macrolepiota procera (Scop.) Singer",
  "basionym": "Agaricus procerus Scop. 1772",
  "taxonomy_domain": "Eukarya",
  "taxonomy_kingdom": "Fungi",
  "taxonomy_phylum": "Basidiomycota",
  "taxonomy_class": "Agaricomycetes",
  "taxonomy_order": "Agaricales",
  "taxonomy_family": "Agaricaceae",
  "taxonomy_genus": "Macrolepiota",
  "taxonomy_species": "procera",
  "synonyms": [
    "Agaricus procerus Scop. 1772",
    "Lepiota procera (Scop.) Gray 1821",
    "Mastocephalus procerus (Scop.) Pat. 1900",
    "Leucocoprinus procerus (Scop.) Pat. 1900"
  ],
  "common_names": [
    "Parasol Mushroom",
    "Parasol",
    "Drumstick Mushroom"
  ],
  "international_names": [
    "Parasol Mushroom (EN)",
    "Coulemelle (FR)",
    "Mazza di tamburo (IT)",
    "Apagador (ES)"
  ],
  "taxonomy_status": {
    "status": "Accepted",
    "variant": "success"
  },
  "quick_id_checklist": [
    {"step": 1, "label": "Large cap 10-30 cm with woolly scales", "status": "pending"},
    {"step": 2, "label": "Movable, double-edged ring", "status": "pending"},
    {"step": 3, "label": "Stem with brown snakeskin pattern", "status": "pending"},
    {"step": 4, "label": "White, free gills", "status": "pending"},
    {"step": 5, "label": "Nutty smell and taste", "status": "pending"},
    {"step": 6, "label": "Flesh stains reddish when cut", "status": "pending"}
  ],
  "identification_difficulty": {
    "status": "Moderate",
    "variant": "warning"
  },
  "time_to_identify_minutes": 5,
  "minimum_equipment_needed": [
    "No equipment required"
  ],
  "field_identifiable": true,
  "confusion_species_list": [
    "Chlorophyllum olivieri (Olive Shaggy Parasol)",
    "Chlorophyllum rhacodes (Shaggy Parasol)",
    "Chlorophyllum venenatum (Vomiter)",
    "Lepiota brunneoincarnata (Deadly Dapperling - deadly)"
  ],
  "confusion_risk_level": {
    "status": "High",
    "variant": "danger"
  },
  "confusion_consequences": [
    {"level": "critical", "type": "Chlorophyllum venenatum", "description": "Vomiter on compost - severe gastrointestinal disturbances"},
    {"level": "critical", "type": "Lepiota species", "description": "Small dapperlings without movable ring - deadly poisonous!"},
    {"level": "low", "type": "Chlorophyllum rhacodes", "description": "Edible, but intolerable raw"}
  ],
  "key_differentiating_features": [
    "Ring MUST be movable",
    "Stem with brown snakeskin pattern",
    "Large caps (up to 30 cm)",
    "Woolly scales on cap",
    "Flesh stains reddish"
  ],
  "habit": "Terrestrial, saprotrophic",
  "growth_form": "Solitary or in groups",
  "symmetry": "radial",
  "size_range": {
    "min": 10,
    "max": 40,
    "unit": "cm"
  },
  "size_typical_cm": 25,
  "basic_shape": "Umbrella-shaped cap mushroom with long stem and ring",
  "height": {
    "min": 15,
    "max": 40,
    "unit": "cm"
  },
  "diameter": {
    "min": 10,
    "max": 30,
    "unit": "cm"
  },
  "surface_type": "Covered with soft, woolly scales",
  "color_primary": "Light brown with darker scales",
  "color_secondary": "Whitish (stem, gills)",
  "primary_structure_present": true,
  "primary_structure_type": "Cap (Pileus)",
  "primary_structure_diameter": {
    "min": 10,
    "max": 30,
    "unit": "cm"
  },
  "primary_structure_shape_young": "Spherical, closed (drumstick)",
  "primary_structure_shape_mature": "Flat expanded with central umbo",
  "primary_structure_surface": "With zoned, soft, woolly scales",
  "primary_structure_color": "Light brown, center darker",
  "support_structure_present": true,
  "support_structure_type": "Stem (Stipe)",
  "support_structure_length": {
    "min": 15,
    "max": 40,
    "unit": "cm"
  },
  "support_structure_thickness": {
    "min": 1,
    "max": 3,
    "unit": "cm"
  },
  "support_structure_shape": "Slender, tough, fibrous, base enlarged",
  "support_structure_color": "Whitish to light brown with brown snakeskin pattern",
  "ring_present": true,
  "ring_type": "Woolly-whitish, double-edged, MOVABLE",
  "ring_position": "Middle third of stem",
  "lamellae_present": true,
  "lamellae_attachment": "Free",
  "lamellae_density": "Crowded",
  "lamellae_color": "White, soft",
  "spore_print_color": "White",
  "smell_description": "Pleasant nutty",
  "smell_comparable_to": "Nuts, pleasantly mushroomy",
  "taste_safe_to_test": true,
  "taste_description": "Pleasant nutty, mild - also edible raw",
  "microscopy_required": false,
  "microscopy_key_features": [
    "Spores 12-18 x 9-12 um",
    "Ellipsoid shaped",
    "White spore print"
  ],
  "spore_measurement_diagnostic": {
    "min": 12,
    "max": 18,
    "unit": "um"
  },
  "appearance_by_season": {
    "spring": "Rare",
    "summer": "Early summer to summer",
    "autumn": "Peak season",
    "winter": "Not present"
  },
  "season_peak_months": [7, 8, 9, 10],
  "nutrition_type": "Saprotrophic",
  "nutrition_type_detail": "Secondary decomposer in meadows and forests",
  "substrate_species": [
    "Forest soils",
    "Meadows",
    "Heathlands",
    "Forest edges"
  ],
  "source": {
    "authors": "Singer, R.",
    "year": 1948,
    "title": "The Agaricales in Modern Taxonomy",
    "journal": "Lilloa",
    "doi": ""
  }
}
