{
  "id": "ganoderma-curtisii",
  "slug": "ganoderma-curtisii",
  "name": "Goldener Lackporling",
  "scientific_name": "Ganoderma curtisii",
  "image": "Ganoderma_curtisii.jpg",
  "description": "Der Goldene Lackporling (Ganoderma curtisii), auch Golden Reishi genannt, ist ein Vitalpilz aus Nordamerika, der dem bekannten Ganoderma lucidum (Reishi) sehr aehnlich ist und dieselben medizinischen Eigenschaften besitzt. Er waechst auf verrottenden Stubben und Wurzeln von Laubhoelzern. Die Art produziert Polysaccharide und Triterpenoide mit breitem Spektrum biologischer Aktivitaeten."
}
